[
  {
    "exists": true,
    "jid": "573164472536@s.whatsapp.net",
    "number": "573164472536"
  },
  {
    "exists": true,
    "jid": "573136937899@s.whatsapp.net",
    "number": "573136937899"
  },
  {
    "exists": true,
    "jid": "573016284309@s.whatsapp.net",
    "number": "573016284309"
  },
  {
    "exists": true,
    "jid": "573128323392@s.whatsapp.net",
    "number": "573128323392"
  },
  {
    "exists": false,
    "jid": "576043657191@s.whatsapp.net",
    "number": "576043657191"
  },
  {
    "exists": true,
    "jid": "573187351528@s.whatsapp.net",
    "number": "573187351528"
  },
  {
    "exists": true,
    "jid": "573154621956@s.whatsapp.net",
    "number": "573154621956"
  },
  {
    "exists": true,
    "jid": "573113720694@s.whatsapp.net",
    "number": "573113720694"
  },
  {
    "exists": true,
    "jid": "573175789939@s.whatsapp.net",
    "number": "573175789939"
  },
  {
    "exists": true,
    "jid": "573163289708@s.whatsapp.net",
    "number": "573163289708"
  },
  {
    "exists": false,
    "jid": "573006135204@s.whatsapp.net",
    "number": "573006135204"
  },
  {
    "exists": true,
    "jid": "573006096018@s.whatsapp.net",
    "number": "573006096018"
  },
  {
    "exists": false,
    "jid": "573187072774@s.whatsapp.net",
    "number": "573187072774"
  },
  {
    "exists": true,
    "jid": "573016369176@s.whatsapp.net",
    "number": "573016369176"
  },
  {
    "exists": false,
    "jid": "573007311241@s.whatsapp.net",
    "number": "573007311241"
  },
  {
    "exists": true,
    "jid": "573005567355@s.whatsapp.net",
    "number": "573005567355"
  },
  {
    "exists": true,
    "jid": "573052569921@s.whatsapp.net",
    "number": "573052569921"
  },
  {
    "exists": false,
    "jid": "573207192868@s.whatsapp.net",
    "number": "573207192868"
  },
  {
    "exists": true,
    "jid": "573024301167@s.whatsapp.net",
    "number": "573024301167"
  },
  {
    "exists": true,
    "jid": "573146309035@s.whatsapp.net",
    "number": "573146309035"
  },
  {
    "exists": true,
    "jid": "573163425990@s.whatsapp.net",
    "number": "573163425990"
  },
  {
    "exists": true,
    "jid": "573017592050@s.whatsapp.net",
    "number": "573017592050"
  },
  {
    "exists": true,
    "jid": "573113783657@s.whatsapp.net",
    "number": "573113783657"
  },
  {
    "exists": false,
    "jid": "584122360669@s.whatsapp.net",
    "number": "58412-2360669"
  },
  {
    "exists": true,
    "jid": "573007825139@s.whatsapp.net",
    "number": "573007825139"
  },
  {
    "exists": true,
    "jid": "573113154963@s.whatsapp.net",
    "number": "573113154963"
  },
  {
    "exists": true,
    "jid": "573107131661@s.whatsapp.net",
    "number": "573107131661"
  },
  {
    "exists": true,
    "jid": "573202370135@s.whatsapp.net",
    "number": "573202370135"
  },
  {
    "exists": true,
    "jid": "573195586446@s.whatsapp.net",
    "number": "573195586446"
  },
  {
    "exists": true,
    "jid": "573168783285@s.whatsapp.net",
    "number": "573168783285"
  },
  {
    "exists": true,
    "jid": "573008389247@s.whatsapp.net",
    "number": "573008389247"
  },
  {
    "exists": true,
    "jid": "573128431400@s.whatsapp.net",
    "number": "573128431400"
  },
  {
    "exists": false,
    "jid": "573218443922@s.whatsapp.net",
    "number": "573218443922"
  },
  {
    "exists": true,
    "jid": "573147917609@s.whatsapp.net",
    "number": "573147917609"
  },
  {
    "exists": true,
    "jid": "573136141359@s.whatsapp.net",
    "number": "573136141359"
  },
  {
    "exists": false,
    "jid": "13176488656@s.whatsapp.net",
    "number": "1317-648-8656"
  },
  {
    "exists": true,
    "jid": "573105389806@s.whatsapp.net",
    "number": "573105389806"
  },
  {
    "exists": false,
    "jid": "576044488324@s.whatsapp.net",
    "number": "576044488324"
  },
  {
    "exists": true,
    "jid": "573164736247@s.whatsapp.net",
    "number": "573164736247"
  },
  {
    "exists": true,
    "jid": "573043439940@s.whatsapp.net",
    "number": "573043439940"
  },
  {
    "exists": true,
    "jid": "573128685019@s.whatsapp.net",
    "number": "573128685019"
  },
  {
    "exists": true,
    "jid": "573103964931@s.whatsapp.net",
    "number": "573103964931"
  },
  {
    "exists": true,
    "jid": "573173687582@s.whatsapp.net",
    "number": "573173687582"
  },
  {
    "exists": true,
    "jid": "573134209502@s.whatsapp.net",
    "number": "573134209502"
  },
  {
    "exists": true,
    "jid": "573128672141@s.whatsapp.net",
    "number": "573128672141"
  },
  {
    "exists": true,
    "jid": "573004940722@s.whatsapp.net",
    "number": "573004940722"
  },
  {
    "exists": true,
    "jid": "573103593353@s.whatsapp.net",
    "number": "573103593353"
  },
  {
    "exists": true,
    "jid": "573217521515@s.whatsapp.net",
    "number": "573217521515"
  },
  {
    "exists": true,
    "jid": "573104062355@s.whatsapp.net",
    "number": "573104062355"
  },
  {
    "exists": true,
    "jid": "573152847965@s.whatsapp.net",
    "number": "573152847965"
  },
  {
    "exists": false,
    "jid": "573154115041@s.whatsapp.net",
    "number": "573154115041"
  },
  {
    "exists": true,
    "jid": "573164829880@s.whatsapp.net",
    "number": "573164829880"
  },
  {
    "exists": true,
    "jid": "573154315027@s.whatsapp.net",
    "number": "573154315027"
  },
  {
    "exists": true,
    "jid": "573006552838@s.whatsapp.net",
    "number": "573006552838"
  },
  {
    "exists": true,
    "jid": "573148144818@s.whatsapp.net",
    "number": "573148144818"
  },
  {
    "exists": true,
    "jid": "573128326870@s.whatsapp.net",
    "number": "573128326870"
  },
  {
    "exists": true,
    "jid": "573168782833@s.whatsapp.net",
    "number": "573168782833"
  },
  {
    "exists": true,
    "jid": "573176494178@s.whatsapp.net",
    "number": "573176494178"
  },
  {
    "exists": true,
    "jid": "573014215209@s.whatsapp.net",
    "number": "573014215209"
  },
  {
    "exists": true,
    "jid": "573007670017@s.whatsapp.net",
    "number": "573007670017"
  },
  {
    "exists": true,
    "jid": "573207311241@s.whatsapp.net",
    "number": "573207311241"
  },
  {
    "exists": true,
    "jid": "573176567959@s.whatsapp.net",
    "number": "573176567959"
  },
  {
    "exists": false,
    "jid": "573192506912@s.whatsapp.net",
    "number": "573192506912"
  },
  {
    "exists": true,
    "jid": "573205891158@s.whatsapp.net",
    "number": "573205891158"
  },
  {
    "exists": true,
    "jid": "13057679166@s.whatsapp.net",
    "number": "1305-767-9166"
  },
  {
    "exists": true,
    "jid": "573183778927@s.whatsapp.net",
    "number": "573183778927"
  },
  {
    "exists": true,
    "jid": "573148264859@s.whatsapp.net",
    "number": "573148264859"
  },
  {
    "exists": false,
    "jid": "573104241979@s.whatsapp.net",
    "number": "573104241979"
  },
  {
    "exists": true,
    "jid": "573176488656@s.whatsapp.net",
    "number": "573176488656"
  },
  {
    "exists": true,
    "jid": "573155833626@s.whatsapp.net",
    "number": "573155833626"
  },
  {
    "exists": false,
    "jid": "573116216145@s.whatsapp.net",
    "number": "573116216145"
  },
  {
    "exists": false,
    "jid": "573125907108@s.whatsapp.net",
    "number": "573125907108"
  },
  {
    "exists": false,
    "jid": "573003441446@s.whatsapp.net",
    "number": "573003441446"
  },
  {
    "exists": true,
    "jid": "573017120564@s.whatsapp.net",
    "number": "573017120564"
  },
  {
    "exists": true,
    "jid": "573122954369@s.whatsapp.net",
    "number": "573122954369"
  },
  {
    "exists": false,
    "jid": "573002688378@s.whatsapp.net",
    "number": "573002688378"
  },
  {
    "exists": true,
    "jid": "573214454353@s.whatsapp.net",
    "number": "573214454353"
  }
]
